aiodatagram/__init__.py
aiodatagram/broadcast.py
aiodatagram/client.py
aiodatagram/endpoint.py
aiodatagram/types.py
aiodatagram-0.0.2.dist-info/METADATA
aiodatagram-0.0.2.dist-info/WHEEL
aiodatagram-0.0.2.dist-info/top_level.txt
aiodatagram-0.0.2.dist-info/RECORD
